pyspark_regression/__init__.py
pyspark_regression/main.py
pyspark_regression-4.1.0.dist-info/licenses/LICENSE
pyspark_regression-4.1.0.dist-info/METADATA
pyspark_regression-4.1.0.dist-info/WHEEL
pyspark_regression-4.1.0.dist-info/top_level.txt
pyspark_regression-4.1.0.dist-info/RECORD
