Metadata-Version: 2.4
Name: pyspark-regression
Version: 4.1.0
Summary: A tool for regression testing Spark Dataframes in Python
Author-email: Forrest Bajbek <forrestbajbek@gmail.com>
Maintainer-email: Forrest Bajbek <forrestbajbek@gmail.com>
License:                                  Apache License
Project-URL: Homepage, https://github.com/forrest-bajbek/pyspark-regression
Project-URL: Repository, https://github.com/forrest-bajbek/pyspark-regression
Project-URL: Issues, https://github.com/forrest-bajbek/pyspark-regression/issues
Project-URL: PyPI, https://pypi.org/project/pyspark-regression/
Project-URL: Documentation, https://forrest-bajbek.github.io/pyspark-regression
Keywords: apache-spark,spark,regression,testing,regression testing,data testing
Classifier: Development Status :: 5 - Production/Stable
Classifier: License :: OSI Approved :: Apache Software License
Classifier: Operating System :: POSIX :: Linux
Classifier: Operating System :: MacOS :: MacOS X
Classifier: Programming Language :: Python :: 3
Classifier: Programming Language :: Python :: 3.10
Requires-Python: >=3.10
License-File: LICENSE
Requires-Dist: pandas
Requires-Dist: pyspark<4,>=3
Requires-Dist: tabulate
Provides-Extra: dev
Requires-Dist: black; extra == "dev"
Requires-Dist: build; extra == "dev"
Requires-Dist: coverage; extra == "dev"
Requires-Dist: flake8; extra == "dev"
Requires-Dist: isort; extra == "dev"
Requires-Dist: mkdocs-material; extra == "dev"
Requires-Dist: mkdocstrings-python; extra == "dev"
Requires-Dist: pre-commit; extra == "dev"
Requires-Dist: pytest-cov; extra == "dev"
Requires-Dist: pytest; extra == "dev"
Requires-Dist: setuptools; extra == "dev"
Requires-Dist: twine; extra == "dev"
Requires-Dist: wheel; extra == "dev"
Dynamic: license-file
